[
  {
    "item_id": "307018712704",
    "current": 17.0,
    "recommended": 14.99,
    "confidence": "med",
    "note": "Top RC Jeanty; Select colored Concourse prizms sell ~12-18 raw, trim to move"
  },
  {
    "item_id": "307006088500",
    "current": 15.83,
    "recommended": 11.99,
    "confidence": "med",
    "note": "Day-3 49ers RB Sig Class auto, thin demand; comps ~8-12 raw"
  },
  {
    "item_id": "306999345372",
    "current": 15.6,
    "recommended": 12.99,
    "confidence": "med",
    "note": "Top WR RC; Select Concourse patch relics sell ~10-15 raw"
  },
  {
    "item_id": "307008900021",
    "current": 14.99,
    "recommended": 12.99,
    "confidence": "low",
    "note": "Wild Card /2 serial of unproven QB; thin comps, niche serial appeal"
  },
  {
    "item_id": "306913934898",
    "current": 14.99,
    "recommended": 11.99,
    "confidence": "med",
    "note": "HOF 20-card common lot; similar lots sell ~8-12 shipped"
  },
  {
    "item_id": "307009715678",
    "current": 14.99,
    "recommended": 11.99,
    "confidence": "low",
    "note": "Optic Orange /79 HOF parallel, niche; est ~8-12 raw"
  },
  {
    "item_id": "307010512881",
    "current": 14.99,
    "recommended": 9.99,
    "confidence": "low",
    "note": "Retired non-HOF Bears auto, low demand; est ~8-10"
  },
  {
    "item_id": "307012024066",
    "current": 14.99,
    "recommended": 14.99,
    "confidence": "med",
    "note": "Josh Allen Chrome Players /150 insert; solid demand, already at market"
  },
  {
    "item_id": "307014465366",
    "current": 14.99,
    "recommended": 3.99,
    "confidence": "high",
    "note": "2023 Score base common; sells ~1-3 raw, way overpriced"
  },
  {
    "item_id": "307014467214",
    "current": 14.99,
    "recommended": 9.99,
    "confidence": "med",
    "note": "Select Orange Burrow parallel; color prizms sell ~6-12 raw"
  }
]
