[
 {
  "image": "output/split_cards/Scan 57/Scan 247_01.jpg",
  "title": "2025 Select Turbocharged Saquon Barkley Orange Eagles Football",
  "price": 7.99,
  "_tier": 7.99,
  "price_src": "tier_fallback"
 },
 {
  "image": "output/split_cards/Scan 57/Scan 247_02.jpg",
  "title": "2025 Select Green Will Johnson RC Cardinals Football",
  "price": 8.99,
  "_tier": 8.99,
  "price_src": "tier_fallback"
 },
 {
  "image": "output/split_cards/Scan 57/Scan 247_03.jpg",
  "title": "2025 Select Green Justin Jefferson Vikings Football",
  "price": 6.99,
  "_tier": 6.99,
  "price_src": "tier_fallback"
 },
 {
  "image": "output/split_cards/Scan 57/Scan 247_04.jpg",
  "title": "2025 Select Future Matthew Golden RC Packers Football",
  "price": 6.99,
  "_tier": 6.99,
  "price_src": "tier_fallback"
 },
 {
  "image": "output/split_cards/Scan 57/Scan 247_05.jpg",
  "title": "2025 Select Green Ashton Jeanty RC Raiders Football",
  "price": 8.99,
  "_tier": 8.99,
  "price_src": "tier_fallback"
 },
 {
  "image": "output/split_cards/Scan 57/Scan 247_06.jpg",
  "title": "2024 Phoenix Blue Ladd McConkey Chargers Football",
  "price": 5.99,
  "_tier": 5.99,
  "price_src": "tier_fallback"
 },
 {
  "image": "output/split_cards/Scan 57/Scan 247_07.jpg",
  "title": "2025 Select Numbers Cam Ward RC Titans Football",
  "price": 6.99,
  "_tier": 6.99,
  "price_src": "tier_fallback"
 },
 {
  "image": "output/split_cards/Scan 57/Scan 247_09.jpg",
  "title": "2023 Mosaic Pink Amon-Ra St. Brown Lions Football",
  "price": 6.99,
  "_tier": 6.99,
  "price_src": "tier_fallback"
 }
]