[
 {
  "image": "output/split_cards/Scan 76/Scan 76_01.jpg",
  "title": "2024 Select Jonathan Taylor Indianapolis Colts Football",
  "price": 4.99,
  "_tier": 4.99,
  "price_src": "tier_fallback"
 },
 {
  "image": "output/split_cards/Scan 76/Scan 76_02.jpg",
  "title": "2024 Select Tri-Color Ricky Pearsall RC San Francisco 49ers Football",
  "price": 7.99,
  "_tier": 7.99,
  "price_src": "tier_fallback"
 },
 {
  "image": "output/split_cards/Scan 76/Scan 76_03.jpg",
  "title": "2025 Select Premier Level Pink Jonathan Taylor Colts Football",
  "price": 6.99,
  "_tier": 6.99,
  "price_src": "tier_fallback"
 },
 {
  "image": "output/split_cards/Scan 76/Scan 76_04.jpg",
  "title": "2024 Select Premier Level Tri-Color Jake Ferguson Cowboys Football",
  "price": 5.99,
  "_tier": 5.99,
  "price_src": "tier_fallback"
 },
 {
  "image": "output/split_cards/Scan 76/Scan 76_05.jpg",
  "title": "2024 Select Field Level Tri-Color Tyler Guyton RC Cowboys Football",
  "price": 8.99,
  "_tier": 8.99,
  "price_src": "tier_fallback"
 },
 {
  "image": "output/split_cards/Scan 76/Scan 76_06.jpg",
  "title": "2025 Select Field Level Isaac TeSlaa RC Detroit Lions Football",
  "price": 8.99,
  "_tier": 8.99,
  "price_src": "tier_fallback"
 },
 {
  "image": "output/split_cards/Scan 76/Scan 76_08.jpg",
  "title": "2025 Select Field Level Tri-Color Adam Thielen Panthers Football",
  "price": 5.99,
  "_tier": 5.99,
  "price_src": "tier_fallback"
 },
 {
  "image": "output/split_cards/Scan 76/Scan 76_09.jpg",
  "title": "2025 Select Premier Level Pink Bhayshul Tuten RC Jaguars Football",
  "price": 8.99,
  "_tier": 8.99,
  "price_src": "tier_fallback"
 }
]