[
 {
  "image": "output/split_cards/Scan 37/Scan 227_01.jpg",
  "title": "2023 Phoenix Thunderbirds Joe Burrow Bengals Football",
  "price": 5.99
 },
 {
  "image": "output/split_cards/Scan 37/Scan 227_02.jpg",
  "title": "2023 Mosaic Joe Burrow Bengals Football",
  "price": 4.99
 },
 {
  "image": "output/split_cards/Scan 37/Scan 227_03.jpg",
  "title": "2023 Select Future C.J. Stroud RC Texans Football",
  "price": 5.99
 },
 {
  "image": "output/split_cards/Scan 37/Scan 227_04.jpg",
  "title": "2023 Score League Leaders Joe Burrow Bengals Football",
  "price": 4.99
 },
 {
  "image": "output/split_cards/Scan 37/Scan 227_05.jpg",
  "title": "2023 Absolute Joe Burrow Bengals Football",
  "price": 4.99
 },
 {
  "image": "output/split_cards/Scan 37/Scan 227_06.jpg",
  "title": "2023 Select Turbocharged C.J. Stroud RC Texans Football",
  "price": 5.99
 },
 {
  "image": "output/split_cards/Scan 37/Scan 227_07.jpg",
  "title": "2023 Score Joe Burrow Bengals Football",
  "price": 4.99
 },
 {
  "image": "output/split_cards/Scan 37/Scan 227_08.jpg",
  "title": "2024 Select Justin Jefferson Vikings Football",
  "price": 4.99
 },
 {
  "image": "output/split_cards/Scan 37/Scan 227_09.jpg",
  "title": "2024 Select Numbers Puka Nacua Rams Football",
  "price": 5.99
 }
]