[
  {
    "image": "output/split_cards/Scan 92/ward_select_field_2.jpg",
    "title": "2025 Panini Select Cam Ward Field Level #426 RC Tennessee Titans Football",
    "price": 6.99
  },
  {
    "image": "output/split_cards/Scan 92/caleb_tc_pick1_2.jpg",
    "title": "2025 Topps Signature Class Caleb Williams Round 1 Pick 1 Insert Chicago Bears Football",
    "price": 22.99
  },
  {
    "image": "output/split_cards/Scan 92/caleb_select_club.jpg",
    "title": "2025 Panini Select Caleb Williams Club Level #226 RC Chicago Bears Football",
    "price": 3.49
  },
  {
    "image": "output/split_cards/Scan 92/caleb_absolute.jpg",
    "title": "2025 Panini Absolute Caleb Williams RC #60 Chicago Bears QB Football",
    "price": 2.49
  },
  {
    "image": "output/split_cards/Scan 92/caleb_select_suite.jpg",
    "title": "2025 Panini Select Caleb Williams Suite Level RC Chicago Bears Football",
    "price": 3.49
  },
  {
    "image": "output/split_cards/Scan 92/mahomes_tc_pick10.jpg",
    "title": "2025 Topps Signature Class Patrick Mahomes Round 1 Pick 10 Insert Kansas City Chiefs Football",
    "price": 1.99
  }
]
