[
  {
    "image": "output/split_cards/Scan 178/card_1.jpg",
    "title": "2025 Topps Signature Class Jayden Daniels RC Round 1 Pick 2 Washington Commanders Football",
    "price": 3.99
  },
  {
    "image": "output/split_cards/Scan 178/card_2.jpg",
    "title": "2025 Topps Signature Class Ja'Marr Chase Round 1 Pick 5 Cincinnati Bengals Football",
    "price": 3.99
  },
  {
    "image": "output/split_cards/Scan 178/card_3.jpg",
    "title": "2025 Topps Signature Class Brock Purdy Round 7 Pick 41 San Francisco 49ers Football",
    "price": 3.99
  },
  {
    "image": "output/split_cards/Scan 178/card_4.jpg",
    "title": "2025 Topps Signature Class Lamar Jackson Round 1 Pick 32 Baltimore Ravens Football",
    "price": 3.99
  },
  {
    "image": "output/split_cards/Scan 178/card_5.jpg",
    "title": "2025 Topps Signature Class Jayden Daniels RC Round 1 Pick 2 Washington Commanders Football",
    "price": 3.99
  },
  {
    "image": "output/split_cards/Scan 178/card_6.jpg",
    "title": "2025 Topps Signature Class Justin Jefferson Round 1 Pick 22 Minnesota Vikings Football",
    "price": 3.99
  },
  {
    "image": "output/split_cards/Scan 178/card_7.jpg",
    "title": "2025 Topps Signature Class CJ Stroud Round 1 Pick 2 Houston Texans Football",
    "price": 3.99
  },
  {
    "image": "output/split_cards/Scan 178/card_8.jpg",
    "title": "2025 Topps Signature Class Patrick Mahomes Round 1 Pick 10 Kansas City Chiefs Football",
    "price": 3.99
  },
  {
    "image": "output/split_cards/Scan 178/card_9.jpg",
    "title": "2025 Topps Signature Class Ashton Jeanty RC Round 1 Pick 6 Las Vegas Raiders Football",
    "price": 3.99
  }
]