{
  "generated_at": "2026-07-09T14:40:06+00:00",
  "window_days": 14,
  "count": 6,
  "applied": false,
  "plans": [
    {
      "item_id": "306941730763",
      "title": "2025 Panini Prizm - Brock Bowers #6 NFL Football",
      "end_date": "2026-07-09T05:24:30.000Z",
      "original_price": 1.99,
      "start_bid": 0.0,
      "bin_price": 1.99,
      "current_price": 1.99,
      "category": "",
      "store_category": "",
      "condition": "",
      "photos": [
        "https://i.ebayimg.com/images/g/rY8AAeSwgntqB-nI/s-l140.jpg"
      ],
      "specifics": {},
      "listing_type": "FixedPriceItem",
      "suggested_price": 2.0
    },
    {
      "item_id": "306941724232",
      "title": "2025 Panini Prizm Draft Picks - Will Howard #83 (RC) Football",
      "end_date": "2026-07-09T05:24:28.000Z",
      "original_price": 1.99,
      "start_bid": 0.0,
      "bin_price": 1.99,
      "current_price": 1.99,
      "category": "",
      "store_category": "",
      "condition": "",
      "photos": [
        "https://i.ebayimg.com/images/g/3cAAAeSwAyNqB-dM/s-l140.jpg"
      ],
      "specifics": {},
      "listing_type": "FixedPriceItem",
      "suggested_price": 2.0
    },
    {
      "item_id": "306931055732",
      "title": "2025 Panini Prizm Draft Picks - Shedeur Sanders #19 (RC) Football",
      "end_date": "2026-07-09T05:24:19.000Z",
      "original_price": 1.99,
      "start_bid": 0.0,
      "bin_price": 1.99,
      "current_price": 1.99,
      "category": "",
      "store_category": "",
      "condition": "",
      "photos": [
        "https://i.ebayimg.com/images/g/w-sAAeSwfqVqAQ4M/s-l140.jpg"
      ],
      "specifics": {},
      "listing_type": "FixedPriceItem",
      "suggested_price": 2.0
    },
    {
      "item_id": "306930745036",
      "title": "2025 Panini Prizm - Rookies Grey Zabel #387 (RC) NFL Football",
      "end_date": "2026-07-09T05:24:17.000Z",
      "original_price": 1.99,
      "start_bid": 0.0,
      "bin_price": 1.99,
      "current_price": 1.99,
      "category": "",
      "store_category": "",
      "condition": "",
      "photos": [
        "https://i.ebayimg.com/images/g/WUYAAeSwd-5qANWf/s-l140.jpg"
      ],
      "specifics": {},
      "listing_type": "FixedPriceItem",
      "suggested_price": 2.0
    },
    {
      "item_id": "306930742908",
      "title": "2025 Panini Prizm - Jared Verse #30 NFL Football",
      "end_date": "2026-07-09T05:24:16.000Z",
      "original_price": 1.99,
      "start_bid": 0.0,
      "bin_price": 1.99,
      "current_price": 1.99,
      "category": "",
      "store_category": "",
      "condition": "",
      "photos": [
        "https://i.ebayimg.com/images/g/yBcAAeSwZZBqANUu/s-l140.jpg"
      ],
      "specifics": {},
      "listing_type": "FixedPriceItem",
      "suggested_price": 2.0
    },
    {
      "item_id": "306914176585",
      "title": "2025 Panini Prizm Draft Picks - Andrew Marsh #157 (RC) Football",
      "end_date": "2026-07-09T03:46:47.000Z",
      "original_price": 1.99,
      "start_bid": 0.0,
      "bin_price": 1.99,
      "current_price": 1.99,
      "category": "",
      "store_category": "",
      "condition": "",
      "photos": [
        "https://i.ebayimg.com/images/g/lTUAAeSwSx9p9hlJ/s-l140.jpg"
      ],
      "specifics": {},
      "listing_type": "FixedPriceItem",
      "suggested_price": 2.0
    }
  ]
}