{
  "generated_at": "2026-05-30T15:17:43+00:00",
  "window_days": 30,
  "totals": {
    "sold_in_window": 64,
    "linked_to_collx": 4,
    "ebay_only": 60
  },
  "mark_sold_in_collx": [
    {
      "collx_id": "1077179423073849344",
      "ebay_item_id": "306968929116",
      "title": "2025 Panini Select - Select Signatures Prizm Ashton Jeanty #SIP-ASJ AU Football",
      "sold_price": 89.99,
      "sold_at": null,
      "buyer": null,
      "already_marked_sold_in_linkage": false
    },
    {
      "collx_id": "1075054826987205632",
      "ebay_item_id": "306955941549",
      "title": "2025 Panini Select - Premier Level Yahya Black #153 Copper Shock Prizm /899 (RC)",
      "sold_price": 2.99,
      "sold_at": null,
      "buyer": null,
      "already_marked_sold_in_linkage": false
    },
    {
      "collx_id": "1075930069532744704",
      "ebay_item_id": "306930909038",
      "title": "2025 Panini Prizm Draft Picks - Bryce Underwood #28 Red Ice Prizm (RC) Football",
      "sold_price": 3.99,
      "sold_at": null,
      "buyer": null,
      "already_marked_sold_in_linkage": false
    },
    {
      "collx_id": "1075183592285413376",
      "ebay_item_id": "306914913674",
      "title": "2025 Panini Select - Premier Level Travis Hunter #128 Pink Shock Prizm (RC)",
      "sold_price": 3.99,
      "sold_at": null,
      "buyer": null,
      "already_marked_sold_in_linkage": false
    }
  ],
  "ebay_only_sales": [
    {
      "ebay_item_id": "306967149076",
      "title": "2024 Panini Select - Concourse Jayden Daniels #26 Red &amp; Yellow Shock Prizm (RC)",
      "sold_price": 7.89,
      "sold_at": null,
      "buyer": null
    },
    {
      "ebay_item_id": "306937604288",
      "title": "2025 Panini Select - Concourse Travis Hunter #28 Pink Shock Prizm (RC) Football",
      "sold_price": 3.99,
      "sold_at": null,
      "buyer": null
    },
    {
      "ebay_item_id": "306930807722",
      "title": "1991-92 Fleer - Pro Vision Magic Johnson #6",
      "sold_price": 1.99,
      "sold_at": null,
      "buyer": null
    },
    {
      "ebay_item_id": "306950542310",
      "title": "2025 Panini Donruss Optic - Caleb Williams #8 Stars Prizm",
      "sold_price": 4.99,
      "sold_at": null,
      "buyer": null
    },
    {
      "ebay_item_id": "306931285504",
      "title": "1991 Fleer - Ken Griffey Jr, Barry Bonds #710 NFL",
      "sold_price": 2.22,
      "sold_at": null,
      "buyer": null
    },
    {
      "ebay_item_id": "306956577061",
      "title": "2025 Panini Prizm - Rookies Shedeur Sanders #302 Lazer Prizm (RC)",
      "sold_price": 11.84,
      "sold_at": null,
      "buyer": null
    },
    {
      "ebay_item_id": "306958364587",
      "title": "2025 Bowman University Chrome - Fernando Mendoza #109 (RC)",
      "sold_price": 12.49,
      "sold_at": null,
      "buyer": null
    },
    {
      "ebay_item_id": "306937669968",
      "title": "2025 Panini Select - Club Level Jayden Daniels #289 Pink Shock Prizm Football",
      "sold_price": 2.99,
      "sold_at": null,
      "buyer": null
    },
    {
      "ebay_item_id": "306956571892",
      "title": "2025 Panini Prizm - Patrick Mahomes II #26 Silver Prizm",
      "sold_price": 6.78,
      "sold_at": null,
      "buyer": null
    },
    {
      "ebay_item_id": "306953884593",
      "title": "2025 Score - Robert Spillane #280 Gold Zone /50",
      "sold_price": 2.99,
      "sold_at": null,
      "buyer": null
    },
    {
      "ebay_item_id": "306937663074",
      "title": "2025 Panini Select - Rookie Swatches TreVeyon Henderson #RSW-THN Red Prizm (MEM,",
      "sold_price": 3.99,
      "sold_at": null,
      "buyer": null
    },
    {
      "ebay_item_id": "306904203738",
      "title": "1994 Steve Emtman Classic Pro Line Live AUTO Autograph Colts NFL Football",
      "sold_price": 8.99,
      "sold_at": null,
      "buyer": null
    },
    {
      "ebay_item_id": "306914911040",
      "title": "2025 Panini Select - Concourse Tetairoa McMillan #44 Pink Shock Prizm (RC)",
      "sold_price": 2.99,
      "sold_at": null,
      "buyer": null
    },
    {
      "ebay_item_id": "306931283327",
      "title": "1990 Ken Griffey Jr Sports Illustrated for Kids Series 1 #158 NFL",
      "sold_price": 2.99,
      "sold_at": null,
      "buyer": null
    },
    {
      "ebay_item_id": "306956963551",
      "title": "2025 Topps Chrome Base Matthew Stafford #169 Rams",
      "sold_price": 14.56,
      "sold_at": null,
      "buyer": null
    },
    {
      "ebay_item_id": "306939342209",
      "title": "2025 Topps Chrome Matthew Golden Pink X-fractor. Packers NFL",
      "sold_price": 4.19,
      "sold_at": null,
      "buyer": null
    },
    {
      "ebay_item_id": "306949802296",
      "title": "2025 Panini Prizm - Sean Taylor #105 Lazer Prizm",
      "sold_price": 4.99,
      "sold_at": null,
      "buyer": null
    },
    {
      "ebay_item_id": "306953120922",
      "title": "2025 Panini Icon Collection Mahomes - Game Gear Patrick Mahomes II #GG-3 (MEM)",
      "sold_price": 9.99,
      "sold_at": null,
      "buyer": null
    },
    {
      "ebay_item_id": "306937601406",
      "title": "2025 Panini Select - Concourse Chuba Hubbard #43 Zebra Prizm",
      "sold_price": 15.5,
      "sold_at": null,
      "buyer": null
    },
    {
      "ebay_item_id": "306937466251",
      "title": "2026 Jeremiyah Love 5 Card Draw Stacked Deck Wild Card RC 3/5 Silver Holo Rookie",
      "sold_price": 13.5,
      "sold_at": null,
      "buyer": null
    },
    {
      "ebay_item_id": "306937452121",
      "title": "2026 Wild Card- Joe Burrow &amp; Justin Jefferson Card 1/1 King NFL",
      "sold_price": 11.5,
      "sold_at": null,
      "buyer": null
    },
    {
      "ebay_item_id": "306931218531",
      "title": "Rickey Henderson New York Yankees 1987 3 Of 7 Card The Press Box",
      "sold_price": 3.99,
      "sold_at": null,
      "buyer": null
    },
    {
      "ebay_item_id": "306947427453",
      "title": "2025 Topps Chrome - Ashton Jeanty Fortune 15 ROOKIE #F15-24 - Raiders",
      "sold_price": 2.99,
      "sold_at": null,
      "buyer": null
    },
    {
      "ebay_item_id": "306945569731",
      "title": "2025 Panini Phoenix - Fuego Signatures Kurtis Rourke #FUS-KRE (AU, RC)",
      "sold_price": 4.99,
      "sold_at": null,
      "buyer": null
    },
    {
      "ebay_item_id": "306914280138",
      "title": "5 Sam Adams Rookie Cards Seattle Seahawks",
      "sold_price": 2.5,
      "sold_at": null,
      "buyer": null
    },
    {
      "ebay_item_id": "306913939866",
      "title": "15 Dan Marino Cards Miami Dolphins Football Card Lot NFL",
      "sold_price": 5.99,
      "sold_at": null,
      "buyer": null
    },
    {
      "ebay_item_id": "306933928667",
      "title": "2024 Panini Prizm Draft Picks - Gold Ice Prizm Lot (16 Cards) Football Card Lot",
      "sold_price": 2.25,
      "sold_at": null,
      "buyer": null
    },
    {
      "ebay_item_id": "306937677187",
      "title": "2025 Panini Phoenix - Thunderbirds Drake Maye #35 Silver Pyramids /299",
      "sold_price": 7.69,
      "sold_at": null,
      "buyer": null
    },
    {
      "ebay_item_id": "306937598270",
      "title": "2025 Panini Select - Concourse Josh Allen #86 Pink Shock Prizm NFL Football",
      "sold_price": 2.99,
      "sold_at": null,
      "buyer": null
    },
    {
      "ebay_item_id": "306937599747",
      "title": "2025 Panini Select - Concourse Ashton Jeanty #4 Pink Shock Prizm (RC) Football",
      "sold_price": 2.99,
      "sold_at": null,
      "buyer": null
    },
    {
      "ebay_item_id": "306937664217",
      "title": "2025 Panini Mosaic - Rookies Cam Ward #382 Camo Pink Mosaic Prizm (RC) Football",
      "sold_price": 2.91,
      "sold_at": null,
      "buyer": null
    },
    {
      "ebay_item_id": "306930560592",
      "title": "2025 Panini Prizm - Rookies Isaac Teslaa #316 (RC) NFL Football",
      "sold_price": 1.99,
      "sold_at": null,
      "buyer": null
    },
    {
      "ebay_item_id": "306913908225",
      "title": "9 Joe Montana Cards 49ers Chiefs Football Card Lot NFL",
      "sold_price": 6.99,
      "sold_at": null,
      "buyer": null
    },
    {
      "ebay_item_id": "306913787569",
      "title": "10 Jim Kelly Cards Buffalo Bills Football Card Lot NFL",
      "sold_price": 4.99,
      "sold_at": null,
      "buyer": null
    },
    {
      "ebay_item_id": "306931291522",
      "title": "1990 Topps - Ken Griffey Jr #336",
      "sold_price": 3.33,
      "sold_at": null,
      "buyer": null
    },
    {
      "ebay_item_id": "306914912556",
      "title": "2025 Panini Select - Concourse Ashton Jeanty #4 Black &amp; Red Shock Prizm (RC)",
      "sold_price": 3.0,
      "sold_at": null,
      "buyer": null
    },
    {
      "ebay_item_id": "306939330491",
      "title": "Topps Chrome Football 2025 Bhayshul Tuten Jaguars Geometric Rookie /99 #389",
      "sold_price": 5.67,
      "sold_at": null,
      "buyer": null
    },
    {
      "ebay_item_id": "306913311444",
      "title": "9 Michael Irvin Cards Dallas Cowboys Football Card Lot NFL",
      "sold_price": 4.99,
      "sold_at": null,
      "buyer": null
    },
    {
      "ebay_item_id": "306930466950",
      "title": "2025 Panini Prizm - Rookies Trey Amos #400 Red Shimmer Prizm /49 (RC)",
      "sold_price": 3.25,
      "sold_at": null,
      "buyer": null
    },
    {
      "ebay_item_id": "306927040476",
      "title": "2026 Wild Card 5 Card Draw Germie Bernard Black Tie Kings #4/4 Steelers RC",
      "sold_price": 7.0,
      "sold_at": null,
      "buyer": null
    },
    {
      "ebay_item_id": "306903933988",
      "title": "8 Cards Roger Craig San Francisco 49ers Minnesota Vikings",
      "sold_price": 1.5,
      "sold_at": null,
      "buyer": null
    },
    {
      "ebay_item_id": "306931229229",
      "title": "1989 Topps Traded - Rickey Henderson #48T Collector's Edition (Tiffany)",
      "sold_price": 12.34,
      "sold_at": null,
      "buyer": null
    },
    {
      "ebay_item_id": "306926030086",
      "title": "2025 Panini Mosaic - Showtime Signatures Aaron Donald SOS-AAD Red &amp; Yellow Prizm",
      "sold_price": 49.99,
      "sold_at": null,
      "buyer": null
    },
    {
      "ebay_item_id": "306931052623",
      "title": "2025 Panini Prizm Draft Picks - Luther Burden #71 Red Ice Prizm (RC)",
      "sold_price": 2.22,
      "sold_at": null,
      "buyer": null
    },
    {
      "ebay_item_id": "306927035291",
      "title": "2026 Wild Card 5 Card Draw Baker Mayfield Stacked Deck Black Tie King #1/1",
      "sold_price": 10.0,
      "sold_at": null,
      "buyer": null
    },
    {
      "ebay_item_id": "306927028439",
      "title": "2026 Wild Card 5 Card Draw Justin Jefferson Stacked Deck Black Tie Aces #2/2",
      "sold_price": 8.0,
      "sold_at": null,
      "buyer": null
    },
    {
      "ebay_item_id": "306930929280",
      "title": "2025 Panini Prizm Draft Picks - Carnell Tate #68 Red Ice Prizm (RC)",
      "sold_price": 3.45,
      "sold_at": null,
      "buyer": null
    },
    {
      "ebay_item_id": "306751048818",
      "title": "EEVEE - Poke Ball Reverse Holo - PSA 9 - 2024 Japanese Terastal Fest ex - #125",
      "sold_price": 15.5,
      "sold_at": null,
      "buyer": null
    },
    {
      "ebay_item_id": "306926059250",
      "title": "2025 Panini Prizm Draft Picks - On Campus Joe Burrow #OC-14",
      "sold_price": 180.0,
      "sold_at": null,
      "buyer": null
    },
    {
      "ebay_item_id": "306914916776",
      "title": "2025 Panini Prizm - Rookies Jalen Milroe #317 Neon Green Pulsar Prizm (RC)",
      "sold_price": 3.99,
      "sold_at": null,
      "buyer": null
    },
    {
      "ebay_item_id": "306914908485",
      "title": "2025 Panini Prizm Draft Picks - Ashton Jeanty #13 Gold Ice Prizm (RC)",
      "sold_price": 2.99,
      "sold_at": null,
      "buyer": null
    },
    {
      "ebay_item_id": "306927289794",
      "title": "2025 Panini Prizm - Rookies Tyler Shough #327 White Disco Prizm (RC)",
      "sold_price": 13.99,
      "sold_at": null,
      "buyer": null
    },
    {
      "ebay_item_id": "306913178483",
      "title": "6 Cards Darrell Green Washington Redskins",
      "sold_price": 1.99,
      "sold_at": null,
      "buyer": null
    },
    {
      "ebay_item_id": "306914170613",
      "title": "2025 Panini Prizm Draft Picks - New Recruits Jeremiah Smith #25 Green Prizm (RC)",
      "sold_price": 4.99,
      "sold_at": null,
      "buyer": null
    },
    {
      "ebay_item_id": "306914248275",
      "title": "2025 Panini Prizm Draft Picks - Carnell Tate #68 Gold Ice Prizm (RC)",
      "sold_price": 2.5,
      "sold_at": null,
      "buyer": null
    },
    {
      "ebay_item_id": "306914175824",
      "title": "2025 Panini Prizm Draft Picks - Instant Impact Cam Ward #II-CWD Gold Ice Prizm",
      "sold_price": 2.0,
      "sold_at": null,
      "buyer": null
    },
    {
      "ebay_item_id": "306914195022",
      "title": "2025 Panini Prizm Draft Picks - Fearless Drew Allar #F-DAR Gold Ice Prizm (RC)",
      "sold_price": 1.99,
      "sold_at": null,
      "buyer": null
    },
    {
      "ebay_item_id": "306914172219",
      "title": "2025 Panini Prizm Draft Picks - Caleb Downs #159 Green Prizm (RC)",
      "sold_price": 1.99,
      "sold_at": null,
      "buyer": null
    },
    {
      "ebay_item_id": "306914214448",
      "title": "2025 Panini Donruss Optic - Rated Rookie Shedeur Sanders #203 Stars Prizm (RC)",
      "sold_price": 9.99,
      "sold_at": null,
      "buyer": null
    },
    {
      "ebay_item_id": "306783987628",
      "title": "Emmitt Smith - 15 x Different Cards, No Duplicates - Dallas Cowboys",
      "sold_price": 2.99,
      "sold_at": null,
      "buyer": null
    }
  ]
}