[
  {
    "applied_at": "2026-05-17T01:25:01.741606+00:00",
    "item_id": "306933928667",
    "title": "2024 Panini Prizm Draft Picks - Gold Ice Prizm Lot (16 Cards)",
    "added": [
      "Year=2024",
      "Set=Prizm",
      "Player=Draft Picks Gold",
      "Athlete=Draft Picks Gold",
      "Parallel/Variety=Gold Ice",
      "Parallel=Gold Ice",
      "Graded=No"
    ],
    "ok": true,
    "ack": "Success",
    "error": null,
    "error_code": null,
    "url": "https://www.ebay.com/itm/2024-Panini-Prizm-Draft-Picks-Gold-Ice-Prizm-Lot-16-Cards--/306933928667"
  },
  {
    "applied_at": "2026-05-17T01:25:04.255981+00:00",
    "item_id": "306934532731",
    "title": "3 Neon Green Pulsar and 5 Purple Wave Prizm 2025 Cards",
    "added": [
      "Year=2025",
      "Manufacturer=Panini",
      "Set=Prizm",
      "Player=Neon Green Pulsar",
      "Athlete=Neon Green Pulsar",
      "Graded=No"
    ],
    "ok": true,
    "ack": "Success",
    "error": null,
    "error_code": null,
    "url": "https://www.ebay.com/itm/3-Neon-Green-Pulsar-and-5-Purple-Wave-Prizm-2025-Cards-/306934532731"
  },
  {
    "applied_at": "2026-05-17T01:25:07.341946+00:00",
    "item_id": "306937452121",
    "title": "2026 Wild Card- Joe Burrow & Justin Jefferson Card 1/1 King",
    "added": [
      "Year=2026",
      "Graded=No"
    ],
    "ok": true,
    "ack": "Success",
    "error": null,
    "error_code": null,
    "url": "https://www.ebay.com/itm/2026-Wild-Card-Joe-Burrow-Justin-Jefferson-Card-1-1-King-/306937452121"
  },
  {
    "applied_at": "2026-05-17T01:25:10.596005+00:00",
    "item_id": "306937463442",
    "title": "2026 Wild Card 5 Card Draw Garrett Nussmeier RC 1/2 Silver Holo Queen",
    "added": [
      "Year=2026",
      "Graded=No"
    ],
    "ok": true,
    "ack": "Success",
    "error": null,
    "error_code": null,
    "url": "https://www.ebay.com/itm/2026-Wild-Card-5-Card-Draw-Garrett-Nussmeier-RC-1-2-Silver-Holo-Queen-/306937463442"
  },
  {
    "applied_at": "2026-05-17T01:25:13.578375+00:00",
    "item_id": "306937466251",
    "title": "2026 Wild Card 5 Card Draw Stacked Deck Jeremiyah Love RC 3/5 Silver Holo Rookie",
    "added": [
      "Year=2026",
      "Graded=No"
    ],
    "ok": true,
    "ack": "Success",
    "error": null,
    "error_code": null,
    "url": "https://www.ebay.com/itm/2026-Wild-Card-5-Card-Draw-Stacked-Deck-Jeremiyah-Love-RC-3-5-Silver-Holo-Rookie-/306937466251"
  },
  {
    "applied_at": "2026-05-17T01:25:15.073183+00:00",
    "item_id": "306937601406",
    "title": "2025 Panini Select - Concourse Chuba Hubbard #43 Zebra Prizm",
    "added": [
      "Year=2025",
      "Graded=No"
    ],
    "ok": false,
    "ack": "Failure",
    "error": "Listing cannot be revised.",
    "error_code": "21916743",
    "url": "https://www.ebay.com/itm/2025-Panini-Select-Concourse-Chuba-Hubbard-43-Zebra-Prizm-/306937601406"
  },
  {
    "applied_at": "2026-05-17T01:25:16.948063+00:00",
    "item_id": "306937606464",
    "title": "2025 Topps Update Series - 1990 Topps Baseball Marcelo Mayer #U90-9 Green...",
    "added": [
      "Year=2025",
      "Graded=No"
    ],
    "ok": true,
    "ack": "Warning",
    "error": "Some custom Item Specific(s) were overwritten by Product Item Specific(s)",
    "error_code": "21920270",
    "url": "https://www.ebay.com/itm/2025-Topps-Update-Series-1990-Topps-Baseball-Marcelo-Mayer-U90-9-Green--/306937606464"
  },
  {
    "applied_at": "2026-05-17T01:25:19.955373+00:00",
    "item_id": "306903937710",
    "title": "Jerome Bettis Notre Dame Los Angeles Rams 10 Cards",
    "added": [
      "Player=Jerome Bettis Notre",
      "Athlete=Jerome Bettis Notre",
      "Graded=No"
    ],
    "ok": true,
    "ack": "Success",
    "error": null,
    "error_code": null,
    "url": "https://www.ebay.com/itm/Jerome-Bettis-Notre-Dame-Los-Angeles-Rams-10-Cards-/306903937710"
  },
  {
    "applied_at": "2026-05-17T01:25:22.493041+00:00",
    "item_id": "306903941543",
    "title": "Tim Brown Los Angeles Raiders Football Card Lot (14) HOF Wide Receiver",
    "added": [
      "Graded=No"
    ],
    "ok": true,
    "ack": "Success",
    "error": null,
    "error_code": null,
    "url": "https://www.ebay.com/itm/Tim-Brown-Los-Angeles-Raiders-Football-Card-Lot-14-HOF-Wide-Receiver-/306903941543"
  },
  {
    "applied_at": "2026-05-17T01:25:24.984214+00:00",
    "item_id": "306903947932",
    "title": "Carl Banks New York Giants Football Card Lot (8) Super Bowl LB",
    "added": [
      "Graded=No"
    ],
    "ok": true,
    "ack": "Success",
    "error": null,
    "error_code": null,
    "url": "https://www.ebay.com/itm/Carl-Banks-New-York-Giants-Football-Card-Lot-8-Super-Bowl-LB-/306903947932"
  },
  {
    "applied_at": "2026-05-17T01:25:28.057665+00:00",
    "item_id": "306904068997",
    "title": "11 Cards Marcus Allen Los Angeles Raiders Kansas City Chiefs",
    "added": [
      "Graded=No"
    ],
    "ok": true,
    "ack": "Success",
    "error": null,
    "error_code": null,
    "url": "https://www.ebay.com/itm/11-Cards-Marcus-Allen-Los-Angeles-Raiders-Kansas-City-Chiefs-/306904068997"
  },
  {
    "applied_at": "2026-05-17T01:25:31.174303+00:00",
    "item_id": "306904078786",
    "title": "7 Cards Steve Atwater Rookie Cards Denver Broncos",
    "added": [
      "Player=Steve Atwater Denver",
      "Athlete=Steve Atwater Denver",
      "Graded=No"
    ],
    "ok": true,
    "ack": "Success",
    "error": null,
    "error_code": null,
    "url": "https://www.ebay.com/itm/7-Cards-Steve-Atwater-Rookie-Cards-Denver-Broncos-/306904078786"
  },
  {
    "applied_at": "2026-05-17T01:25:33.725195+00:00",
    "item_id": "306904174454",
    "title": "7 Cards Boomer Esiason Cincinnati Bengals New York Jets",
    "added": [
      "Graded=No"
    ],
    "ok": true,
    "ack": "Success",
    "error": null,
    "error_code": null,
    "url": "https://www.ebay.com/itm/7-Cards-Boomer-Esiason-Cincinnati-Bengals-New-York-Jets-/306904174454"
  },
  {
    "applied_at": "2026-05-17T01:25:36.802624+00:00",
    "item_id": "306904189481",
    "title": "4 Aaron Glenn Rookie Cards New York Jets",
    "added": [
      "Player=Aaron Glenn New",
      "Athlete=Aaron Glenn New",
      "Graded=No"
    ],
    "ok": true,
    "ack": "Success",
    "error": null,
    "error_code": null,
    "url": "https://www.ebay.com/itm/4-Aaron-Glenn-Rookie-Cards-New-York-Jets-/306904189481"
  },
  {
    "applied_at": "2026-05-17T01:25:39.988112+00:00",
    "item_id": "306904203738",
    "title": "1994 Classic Pro Line Live - Autograph - Steve Emtman",
    "added": [
      "Year=1994"
    ],
    "ok": true,
    "ack": "Warning",
    "error": "Some custom Item Specific(s) were overwritten by Product Item Specific(s)",
    "error_code": "21920270",
    "url": "https://www.ebay.com/itm/1994-Classic-Pro-Line-Live-Autograph-Steve-Emtman--/306904203738"
  },
  {
    "applied_at": "2026-05-17T01:25:43.647611+00:00",
    "item_id": "306904215389",
    "title": "12 Jim Everett Cards Los Angeles Rams New Orleans Saints",
    "added": [
      "Graded=No"
    ],
    "ok": true,
    "ack": "Success",
    "error": null,
    "error_code": null,
    "url": "https://www.ebay.com/itm/12-Jim-Everett-Cards-Los-Angeles-Rams-New-Orleans-Saints-/306904215389"
  },
  {
    "applied_at": "2026-05-17T01:25:46.705762+00:00",
    "item_id": "306913168494",
    "title": "15 Charles Haley Cards San Francisco 49ers Dallas Cowboys",
    "added": [
      "Player=Charles Haley San",
      "Athlete=Charles Haley San",
      "Graded=No"
    ],
    "ok": true,
    "ack": "Success",
    "error": null,
    "error_code": null,
    "url": "https://www.ebay.com/itm/15-Charles-Haley-Cards-San-Francisco-49ers-Dallas-Cowboys-/306913168494"
  },
  {
    "applied_at": "2026-05-17T01:25:49.170742+00:00",
    "item_id": "306913186982",
    "title": "11 Mel Gray Cards Detroit Lions Football Card Lot NFL",
    "added": [
      "Graded=No"
    ],
    "ok": true,
    "ack": "Success",
    "error": null,
    "error_code": null,
    "url": "https://www.ebay.com/itm/11-Mel-Gray-Cards-Detroit-Lions-Football-Card-Lot-NFL-/306913186982"
  },
  {
    "applied_at": "2026-05-17T01:25:51.652027+00:00",
    "item_id": "306913307606",
    "title": "5 Bobby Humphrey Cards Denver Broncos Football Card Lot NFL",
    "added": [
      "Graded=No"
    ],
    "ok": true,
    "ack": "Success",
    "error": null,
    "error_code": null,
    "url": "https://www.ebay.com/itm/5-Bobby-Humphrey-Cards-Denver-Broncos-Football-Card-Lot-NFL-/306913307606"
  },
  {
    "applied_at": "2026-05-17T01:25:54.761256+00:00",
    "item_id": "306913787569",
    "title": "10 Jim Kelly Cards Buffalo Bills Football Card Lot NFL",
    "added": [
      "Graded=No"
    ],
    "ok": true,
    "ack": "Success",
    "error": null,
    "error_code": null,
    "url": "https://www.ebay.com/itm/10-Jim-Kelly-Cards-Buffalo-Bills-Football-Card-Lot-NFL-/306913787569"
  },
  {
    "applied_at": "2026-05-17T01:25:56.676478+00:00",
    "item_id": "306913790653",
    "title": "11 Raghib And Quadry Ismail Cards Raiders Vikings",
    "added": [
      "Player=Raghib Quadry Ismail",
      "Athlete=Raghib Quadry Ismail",
      "Graded=No"
    ],
    "ok": true,
    "ack": "Success",
    "error": null,
    "error_code": null,
    "url": "https://www.ebay.com/itm/11-Raghib-And-Quadry-Ismail-Cards-Raiders-Vikings-/306913790653"
  },
  {
    "applied_at": "2026-05-17T01:25:58.473658+00:00",
    "item_id": "306913845449",
    "title": "3 Steve Largent Cards Seattle Seahawks Football Card Lot NFL",
    "added": [
      "Graded=No"
    ],
    "ok": true,
    "ack": "Success",
    "error": null,
    "error_code": null,
    "url": "https://www.ebay.com/itm/3-Steve-Largent-Cards-Seattle-Seahawks-Football-Card-Lot-NFL-/306913845449"
  },
  {
    "applied_at": "2026-05-17T01:26:00.994071+00:00",
    "item_id": "306913853080",
    "title": "9 Ronnie Lott Cards 49ers Raiders Jets Football Card Lot NFL",
    "added": [
      "Player=Ronnie Lott Raiders",
      "Athlete=Ronnie Lott Raiders",
      "Graded=No"
    ],
    "ok": true,
    "ack": "Success",
    "error": null,
    "error_code": null,
    "url": "https://www.ebay.com/itm/9-Ronnie-Lott-Cards-49ers-Raiders-Jets-Football-Card-Lot-NFL-/306913853080"
  },
  {
    "applied_at": "2026-05-17T01:26:02.744287+00:00",
    "item_id": "306913902750",
    "title": "7 Howie Long Cards Raiders",
    "added": [
      "Graded=No"
    ],
    "ok": true,
    "ack": "Success",
    "error": null,
    "error_code": null,
    "url": "https://www.ebay.com/itm/7-Howie-Long-Cards-Raiders-/306913902750"
  },
  {
    "applied_at": "2026-05-17T01:26:04.462188+00:00",
    "item_id": "306913908225",
    "title": "9 Joe Montana Cards 49ers Chiefs",
    "added": [
      "Graded=No"
    ],
    "ok": true,
    "ack": "Success",
    "error": null,
    "error_code": null,
    "url": "https://www.ebay.com/itm/9-Joe-Montana-Cards-49ers-Chiefs-/306913908225"
  },
  {
    "applied_at": "2026-05-17T01:26:29.808119+00:00",
    "item_id": "306933928667",
    "title": "2024 Panini Prizm Draft Picks - Gold Ice Prizm Lot (16 Cards)",
    "added": [
      "Year=2024",
      "Set=Prizm",
      "Player=Draft Picks Gold",
      "Athlete=Draft Picks Gold",
      "Parallel/Variety=Gold Ice",
      "Parallel=Gold Ice",
      "Graded=No"
    ],
    "ok": true,
    "ack": "Success",
    "error": null,
    "error_code": null,
    "url": "https://www.ebay.com/itm/2024-Panini-Prizm-Draft-Picks-Gold-Ice-Prizm-Lot-16-Cards--/306933928667"
  },
  {
    "applied_at": "2026-05-17T01:26:32.325615+00:00",
    "item_id": "306934532731",
    "title": "3 Neon Green Pulsar and 5 Purple Wave Prizm 2025 Cards",
    "added": [
      "Year=2025",
      "Manufacturer=Panini",
      "Set=Prizm",
      "Player=Neon Green Pulsar",
      "Athlete=Neon Green Pulsar",
      "Graded=No"
    ],
    "ok": true,
    "ack": "Success",
    "error": null,
    "error_code": null,
    "url": "https://www.ebay.com/itm/3-Neon-Green-Pulsar-and-5-Purple-Wave-Prizm-2025-Cards-/306934532731"
  },
  {
    "applied_at": "2026-05-17T01:26:34.141810+00:00",
    "item_id": "306937452121",
    "title": "2026 Wild Card- Joe Burrow & Justin Jefferson Card 1/1 King",
    "added": [
      "Year=2026",
      "Graded=No"
    ],
    "ok": true,
    "ack": "Success",
    "error": null,
    "error_code": null,
    "url": "https://www.ebay.com/itm/2026-Wild-Card-Joe-Burrow-Justin-Jefferson-Card-1-1-King-/306937452121"
  },
  {
    "applied_at": "2026-05-17T01:26:37.127037+00:00",
    "item_id": "306937463442",
    "title": "2026 Wild Card 5 Card Draw Garrett Nussmeier RC 1/2 Silver Holo Queen",
    "added": [
      "Year=2026",
      "Graded=No"
    ],
    "ok": true,
    "ack": "Success",
    "error": null,
    "error_code": null,
    "url": "https://www.ebay.com/itm/2026-Wild-Card-5-Card-Draw-Garrett-Nussmeier-RC-1-2-Silver-Holo-Queen-/306937463442"
  },
  {
    "applied_at": "2026-05-17T01:26:39.525781+00:00",
    "item_id": "306937466251",
    "title": "2026 Wild Card 5 Card Draw Stacked Deck Jeremiyah Love RC 3/5 Silver Holo Rookie",
    "added": [
      "Year=2026",
      "Graded=No"
    ],
    "ok": true,
    "ack": "Success",
    "error": null,
    "error_code": null,
    "url": "https://www.ebay.com/itm/2026-Wild-Card-5-Card-Draw-Stacked-Deck-Jeremiyah-Love-RC-3-5-Silver-Holo-Rookie-/306937466251"
  },
  {
    "applied_at": "2026-05-17T01:26:41.025005+00:00",
    "item_id": "306937601406",
    "title": "2025 Panini Select - Concourse Chuba Hubbard #43 Zebra Prizm",
    "added": [
      "Year=2025",
      "Graded=No"
    ],
    "ok": false,
    "ack": "Failure",
    "error": "Listing cannot be revised.",
    "error_code": "21916743",
    "url": "https://www.ebay.com/itm/2025-Panini-Select-Concourse-Chuba-Hubbard-43-Zebra-Prizm-/306937601406"
  },
  {
    "applied_at": "2026-05-17T01:26:42.831419+00:00",
    "item_id": "306937606464",
    "title": "2025 Topps Update Series - 1990 Topps Baseball Marcelo Mayer #U90-9 Green...",
    "added": [
      "Year=2025",
      "Graded=No"
    ],
    "ok": true,
    "ack": "Warning",
    "error": "Some custom Item Specific(s) were overwritten by Product Item Specific(s)",
    "error_code": "21920270",
    "url": "https://www.ebay.com/itm/2025-Topps-Update-Series-1990-Topps-Baseball-Marcelo-Mayer-U90-9-Green--/306937606464"
  },
  {
    "applied_at": "2026-05-17T01:26:44.747155+00:00",
    "item_id": "306903937710",
    "title": "Jerome Bettis Notre Dame Los Angeles Rams 10 Cards",
    "added": [
      "Player=Jerome Bettis Notre",
      "Athlete=Jerome Bettis Notre",
      "Graded=No"
    ],
    "ok": true,
    "ack": "Success",
    "error": null,
    "error_code": null,
    "url": "https://www.ebay.com/itm/Jerome-Bettis-Notre-Dame-Los-Angeles-Rams-10-Cards-/306903937710"
  },
  {
    "applied_at": "2026-05-17T01:26:47.163151+00:00",
    "item_id": "306903941543",
    "title": "Tim Brown Los Angeles Raiders Football Card Lot (14) HOF Wide Receiver",
    "added": [
      "Graded=No"
    ],
    "ok": true,
    "ack": "Success",
    "error": null,
    "error_code": null,
    "url": "https://www.ebay.com/itm/Tim-Brown-Los-Angeles-Raiders-Football-Card-Lot-14-HOF-Wide-Receiver-/306903941543"
  },
  {
    "applied_at": "2026-05-17T01:26:48.916529+00:00",
    "item_id": "306903947932",
    "title": "Carl Banks New York Giants Football Card Lot (8) Super Bowl LB",
    "added": [
      "Graded=No"
    ],
    "ok": true,
    "ack": "Success",
    "error": null,
    "error_code": null,
    "url": "https://www.ebay.com/itm/Carl-Banks-New-York-Giants-Football-Card-Lot-8-Super-Bowl-LB-/306903947932"
  },
  {
    "applied_at": "2026-05-17T01:26:50.631873+00:00",
    "item_id": "306904068997",
    "title": "11 Cards Marcus Allen Los Angeles Raiders Kansas City Chiefs",
    "added": [
      "Graded=No"
    ],
    "ok": true,
    "ack": "Success",
    "error": null,
    "error_code": null,
    "url": "https://www.ebay.com/itm/11-Cards-Marcus-Allen-Los-Angeles-Raiders-Kansas-City-Chiefs-/306904068997"
  },
  {
    "applied_at": "2026-05-17T01:26:53.530295+00:00",
    "item_id": "306904078786",
    "title": "7 Cards Steve Atwater Rookie Cards Denver Broncos",
    "added": [
      "Player=Steve Atwater Denver",
      "Athlete=Steve Atwater Denver",
      "Graded=No"
    ],
    "ok": true,
    "ack": "Success",
    "error": null,
    "error_code": null,
    "url": "https://www.ebay.com/itm/7-Cards-Steve-Atwater-Rookie-Cards-Denver-Broncos-/306904078786"
  },
  {
    "applied_at": "2026-05-17T01:26:56.757091+00:00",
    "item_id": "306904174454",
    "title": "7 Cards Boomer Esiason Cincinnati Bengals New York Jets",
    "added": [
      "Graded=No"
    ],
    "ok": true,
    "ack": "Success",
    "error": null,
    "error_code": null,
    "url": "https://www.ebay.com/itm/7-Cards-Boomer-Esiason-Cincinnati-Bengals-New-York-Jets-/306904174454"
  },
  {
    "applied_at": "2026-05-17T01:26:59.786405+00:00",
    "item_id": "306904189481",
    "title": "4 Aaron Glenn Rookie Cards New York Jets",
    "added": [
      "Player=Aaron Glenn New",
      "Athlete=Aaron Glenn New",
      "Graded=No"
    ],
    "ok": true,
    "ack": "Success",
    "error": null,
    "error_code": null,
    "url": "https://www.ebay.com/itm/4-Aaron-Glenn-Rookie-Cards-New-York-Jets-/306904189481"
  },
  {
    "applied_at": "2026-05-17T01:27:01.523810+00:00",
    "item_id": "306904203738",
    "title": "1994 Classic Pro Line Live - Autograph - Steve Emtman",
    "added": [
      "Year=1994"
    ],
    "ok": true,
    "ack": "Warning",
    "error": "Some custom Item Specific(s) were overwritten by Product Item Specific(s)",
    "error_code": "21920270",
    "url": "https://www.ebay.com/itm/1994-Classic-Pro-Line-Live-Autograph-Steve-Emtman--/306904203738"
  },
  {
    "applied_at": "2026-05-17T01:27:03.351861+00:00",
    "item_id": "306904215389",
    "title": "12 Jim Everett Cards Los Angeles Rams New Orleans Saints",
    "added": [
      "Graded=No"
    ],
    "ok": true,
    "ack": "Success",
    "error": null,
    "error_code": null,
    "url": "https://www.ebay.com/itm/12-Jim-Everett-Cards-Los-Angeles-Rams-New-Orleans-Saints-/306904215389"
  },
  {
    "applied_at": "2026-05-17T01:27:05.938442+00:00",
    "item_id": "306913168494",
    "title": "15 Charles Haley Cards San Francisco 49ers Dallas Cowboys",
    "added": [
      "Player=Charles Haley San",
      "Athlete=Charles Haley San",
      "Graded=No"
    ],
    "ok": true,
    "ack": "Success",
    "error": null,
    "error_code": null,
    "url": "https://www.ebay.com/itm/15-Charles-Haley-Cards-San-Francisco-49ers-Dallas-Cowboys-/306913168494"
  },
  {
    "applied_at": "2026-05-17T01:27:08.634078+00:00",
    "item_id": "306913186982",
    "title": "11 Mel Gray Cards Detroit Lions Football Card Lot NFL",
    "added": [
      "Graded=No"
    ],
    "ok": true,
    "ack": "Success",
    "error": null,
    "error_code": null,
    "url": "https://www.ebay.com/itm/11-Mel-Gray-Cards-Detroit-Lions-Football-Card-Lot-NFL-/306913186982"
  },
  {
    "applied_at": "2026-05-17T01:27:10.406416+00:00",
    "item_id": "306913307606",
    "title": "5 Bobby Humphrey Cards Denver Broncos Football Card Lot NFL",
    "added": [
      "Graded=No"
    ],
    "ok": true,
    "ack": "Success",
    "error": null,
    "error_code": null,
    "url": "https://www.ebay.com/itm/5-Bobby-Humphrey-Cards-Denver-Broncos-Football-Card-Lot-NFL-/306913307606"
  },
  {
    "applied_at": "2026-05-17T01:27:12.869644+00:00",
    "item_id": "306913787569",
    "title": "10 Jim Kelly Cards Buffalo Bills Football Card Lot NFL",
    "added": [
      "Graded=No"
    ],
    "ok": true,
    "ack": "Success",
    "error": null,
    "error_code": null,
    "url": "https://www.ebay.com/itm/10-Jim-Kelly-Cards-Buffalo-Bills-Football-Card-Lot-NFL-/306913787569"
  },
  {
    "applied_at": "2026-05-17T01:27:15.366800+00:00",
    "item_id": "306913790653",
    "title": "11 Raghib And Quadry Ismail Cards Raiders Vikings",
    "added": [
      "Player=Raghib Quadry Ismail",
      "Athlete=Raghib Quadry Ismail",
      "Graded=No"
    ],
    "ok": true,
    "ack": "Success",
    "error": null,
    "error_code": null,
    "url": "https://www.ebay.com/itm/11-Raghib-And-Quadry-Ismail-Cards-Raiders-Vikings-/306913790653"
  },
  {
    "applied_at": "2026-05-17T01:27:17.173920+00:00",
    "item_id": "306913845449",
    "title": "3 Steve Largent Cards Seattle Seahawks Football Card Lot NFL",
    "added": [
      "Graded=No"
    ],
    "ok": true,
    "ack": "Success",
    "error": null,
    "error_code": null,
    "url": "https://www.ebay.com/itm/3-Steve-Largent-Cards-Seattle-Seahawks-Football-Card-Lot-NFL-/306913845449"
  },
  {
    "applied_at": "2026-05-17T01:27:19.618263+00:00",
    "item_id": "306913853080",
    "title": "9 Ronnie Lott Cards 49ers Raiders Jets Football Card Lot NFL",
    "added": [
      "Player=Ronnie Lott Raiders",
      "Athlete=Ronnie Lott Raiders",
      "Graded=No"
    ],
    "ok": true,
    "ack": "Success",
    "error": null,
    "error_code": null,
    "url": "https://www.ebay.com/itm/9-Ronnie-Lott-Cards-49ers-Raiders-Jets-Football-Card-Lot-NFL-/306913853080"
  },
  {
    "applied_at": "2026-05-17T01:27:22.202269+00:00",
    "item_id": "306913902750",
    "title": "7 Howie Long Cards Raiders",
    "added": [
      "Graded=No"
    ],
    "ok": true,
    "ack": "Success",
    "error": null,
    "error_code": null,
    "url": "https://www.ebay.com/itm/7-Howie-Long-Cards-Raiders-/306913902750"
  },
  {
    "applied_at": "2026-05-17T01:27:24.842822+00:00",
    "item_id": "306913908225",
    "title": "9 Joe Montana Cards 49ers Chiefs",
    "added": [
      "Graded=No"
    ],
    "ok": true,
    "ack": "Success",
    "error": null,
    "error_code": null,
    "url": "https://www.ebay.com/itm/9-Joe-Montana-Cards-49ers-Chiefs-/306913908225"
  },
  {
    "applied_at": "2026-05-17T01:27:28.235059+00:00",
    "item_id": "306933928667",
    "title": "2024 Panini Prizm Draft Picks - Gold Ice Prizm Lot (16 Cards)",
    "added": [
      "Year=2024",
      "Set=Prizm",
      "Player=Draft Picks Gold",
      "Athlete=Draft Picks Gold",
      "Parallel/Variety=Gold Ice",
      "Parallel=Gold Ice",
      "Graded=No"
    ],
    "ok": true,
    "ack": "Success",
    "error": null,
    "error_code": null,
    "url": "https://www.ebay.com/itm/2024-Panini-Prizm-Draft-Picks-Gold-Ice-Prizm-Lot-16-Cards--/306933928667"
  },
  {
    "applied_at": "2026-05-17T01:27:31.143663+00:00",
    "item_id": "306934532731",
    "title": "3 Neon Green Pulsar and 5 Purple Wave Prizm 2025 Cards",
    "added": [
      "Year=2025",
      "Manufacturer=Panini",
      "Set=Prizm",
      "Player=Neon Green Pulsar",
      "Athlete=Neon Green Pulsar",
      "Graded=No"
    ],
    "ok": true,
    "ack": "Success",
    "error": null,
    "error_code": null,
    "url": "https://www.ebay.com/itm/3-Neon-Green-Pulsar-and-5-Purple-Wave-Prizm-2025-Cards-/306934532731"
  },
  {
    "applied_at": "2026-05-17T01:27:33.527901+00:00",
    "item_id": "306937452121",
    "title": "2026 Wild Card- Joe Burrow & Justin Jefferson Card 1/1 King",
    "added": [
      "Year=2026",
      "Graded=No"
    ],
    "ok": true,
    "ack": "Success",
    "error": null,
    "error_code": null,
    "url": "https://www.ebay.com/itm/2026-Wild-Card-Joe-Burrow-Justin-Jefferson-Card-1-1-King-/306937452121"
  },
  {
    "applied_at": "2026-05-17T01:27:35.434327+00:00",
    "item_id": "306937463442",
    "title": "2026 Wild Card 5 Card Draw Garrett Nussmeier RC 1/2 Silver Holo Queen",
    "added": [
      "Year=2026",
      "Graded=No"
    ],
    "ok": true,
    "ack": "Success",
    "error": null,
    "error_code": null,
    "url": "https://www.ebay.com/itm/2026-Wild-Card-5-Card-Draw-Garrett-Nussmeier-RC-1-2-Silver-Holo-Queen-/306937463442"
  },
  {
    "applied_at": "2026-05-17T01:27:37.308117+00:00",
    "item_id": "306937466251",
    "title": "2026 Wild Card 5 Card Draw Stacked Deck Jeremiyah Love RC 3/5 Silver Holo Rookie",
    "added": [
      "Year=2026",
      "Graded=No"
    ],
    "ok": true,
    "ack": "Success",
    "error": null,
    "error_code": null,
    "url": "https://www.ebay.com/itm/2026-Wild-Card-5-Card-Draw-Stacked-Deck-Jeremiyah-Love-RC-3-5-Silver-Holo-Rookie-/306937466251"
  },
  {
    "applied_at": "2026-05-17T01:27:38.388160+00:00",
    "item_id": "306937601406",
    "title": "2025 Panini Select - Concourse Chuba Hubbard #43 Zebra Prizm",
    "added": [
      "Year=2025",
      "Graded=No"
    ],
    "ok": false,
    "ack": "Failure",
    "error": "Listing cannot be revised.",
    "error_code": "21916743",
    "url": "https://www.ebay.com/itm/2025-Panini-Select-Concourse-Chuba-Hubbard-43-Zebra-Prizm-/306937601406"
  },
  {
    "applied_at": "2026-05-17T01:27:40.877737+00:00",
    "item_id": "306937606464",
    "title": "2025 Topps Update Series - 1990 Topps Baseball Marcelo Mayer #U90-9 Green...",
    "added": [
      "Year=2025",
      "Graded=No"
    ],
    "ok": true,
    "ack": "Warning",
    "error": "Some custom Item Specific(s) were overwritten by Product Item Specific(s)",
    "error_code": "21920270",
    "url": "https://www.ebay.com/itm/2025-Topps-Update-Series-1990-Topps-Baseball-Marcelo-Mayer-U90-9-Green--/306937606464"
  },
  {
    "applied_at": "2026-05-17T01:27:43.472266+00:00",
    "item_id": "306903937710",
    "title": "Jerome Bettis Notre Dame Los Angeles Rams 10 Cards",
    "added": [
      "Player=Jerome Bettis Notre",
      "Athlete=Jerome Bettis Notre",
      "Graded=No"
    ],
    "ok": true,
    "ack": "Success",
    "error": null,
    "error_code": null,
    "url": "https://www.ebay.com/itm/Jerome-Bettis-Notre-Dame-Los-Angeles-Rams-10-Cards-/306903937710"
  },
  {
    "applied_at": "2026-05-17T01:27:45.979671+00:00",
    "item_id": "306903941543",
    "title": "Tim Brown Los Angeles Raiders Football Card Lot (14) HOF Wide Receiver",
    "added": [
      "Graded=No"
    ],
    "ok": true,
    "ack": "Success",
    "error": null,
    "error_code": null,
    "url": "https://www.ebay.com/itm/Tim-Brown-Los-Angeles-Raiders-Football-Card-Lot-14-HOF-Wide-Receiver-/306903941543"
  },
  {
    "applied_at": "2026-05-17T01:27:49.078923+00:00",
    "item_id": "306903947932",
    "title": "Carl Banks New York Giants Football Card Lot (8) Super Bowl LB",
    "added": [
      "Graded=No"
    ],
    "ok": true,
    "ack": "Success",
    "error": null,
    "error_code": null,
    "url": "https://www.ebay.com/itm/Carl-Banks-New-York-Giants-Football-Card-Lot-8-Super-Bowl-LB-/306903947932"
  },
  {
    "applied_at": "2026-05-17T01:27:51.756248+00:00",
    "item_id": "306904068997",
    "title": "11 Cards Marcus Allen Los Angeles Raiders Kansas City Chiefs",
    "added": [
      "Graded=No"
    ],
    "ok": true,
    "ack": "Success",
    "error": null,
    "error_code": null,
    "url": "https://www.ebay.com/itm/11-Cards-Marcus-Allen-Los-Angeles-Raiders-Kansas-City-Chiefs-/306904068997"
  },
  {
    "applied_at": "2026-05-17T01:27:54.257578+00:00",
    "item_id": "306904078786",
    "title": "7 Cards Steve Atwater Rookie Cards Denver Broncos",
    "added": [
      "Player=Steve Atwater Denver",
      "Athlete=Steve Atwater Denver",
      "Graded=No"
    ],
    "ok": true,
    "ack": "Success",
    "error": null,
    "error_code": null,
    "url": "https://www.ebay.com/itm/7-Cards-Steve-Atwater-Rookie-Cards-Denver-Broncos-/306904078786"
  },
  {
    "applied_at": "2026-05-17T01:27:56.004653+00:00",
    "item_id": "306904174454",
    "title": "7 Cards Boomer Esiason Cincinnati Bengals New York Jets",
    "added": [
      "Graded=No"
    ],
    "ok": true,
    "ack": "Success",
    "error": null,
    "error_code": null,
    "url": "https://www.ebay.com/itm/7-Cards-Boomer-Esiason-Cincinnati-Bengals-New-York-Jets-/306904174454"
  },
  {
    "applied_at": "2026-05-17T01:27:57.938574+00:00",
    "item_id": "306904189481",
    "title": "4 Aaron Glenn Rookie Cards New York Jets",
    "added": [
      "Player=Aaron Glenn New",
      "Athlete=Aaron Glenn New",
      "Graded=No"
    ],
    "ok": true,
    "ack": "Success",
    "error": null,
    "error_code": null,
    "url": "https://www.ebay.com/itm/4-Aaron-Glenn-Rookie-Cards-New-York-Jets-/306904189481"
  },
  {
    "applied_at": "2026-05-17T01:27:59.760943+00:00",
    "item_id": "306904203738",
    "title": "1994 Classic Pro Line Live - Autograph - Steve Emtman",
    "added": [
      "Year=1994"
    ],
    "ok": true,
    "ack": "Warning",
    "error": "Some custom Item Specific(s) were overwritten by Product Item Specific(s)",
    "error_code": "21920270",
    "url": "https://www.ebay.com/itm/1994-Classic-Pro-Line-Live-Autograph-Steve-Emtman--/306904203738"
  },
  {
    "applied_at": "2026-05-17T01:28:02.278871+00:00",
    "item_id": "306904215389",
    "title": "12 Jim Everett Cards Los Angeles Rams New Orleans Saints",
    "added": [
      "Graded=No"
    ],
    "ok": true,
    "ack": "Success",
    "error": null,
    "error_code": null,
    "url": "https://www.ebay.com/itm/12-Jim-Everett-Cards-Los-Angeles-Rams-New-Orleans-Saints-/306904215389"
  },
  {
    "applied_at": "2026-05-17T01:28:05.419127+00:00",
    "item_id": "306913168494",
    "title": "15 Charles Haley Cards San Francisco 49ers Dallas Cowboys",
    "added": [
      "Player=Charles Haley San",
      "Athlete=Charles Haley San",
      "Graded=No"
    ],
    "ok": true,
    "ack": "Success",
    "error": null,
    "error_code": null,
    "url": "https://www.ebay.com/itm/15-Charles-Haley-Cards-San-Francisco-49ers-Dallas-Cowboys-/306913168494"
  },
  {
    "applied_at": "2026-05-17T01:28:07.216538+00:00",
    "item_id": "306913186982",
    "title": "11 Mel Gray Cards Detroit Lions Football Card Lot NFL",
    "added": [
      "Graded=No"
    ],
    "ok": true,
    "ack": "Success",
    "error": null,
    "error_code": null,
    "url": "https://www.ebay.com/itm/11-Mel-Gray-Cards-Detroit-Lions-Football-Card-Lot-NFL-/306913186982"
  },
  {
    "applied_at": "2026-05-17T01:28:10.414821+00:00",
    "item_id": "306913307606",
    "title": "5 Bobby Humphrey Cards Denver Broncos Football Card Lot NFL",
    "added": [
      "Graded=No"
    ],
    "ok": true,
    "ack": "Success",
    "error": null,
    "error_code": null,
    "url": "https://www.ebay.com/itm/5-Bobby-Humphrey-Cards-Denver-Broncos-Football-Card-Lot-NFL-/306913307606"
  },
  {
    "applied_at": "2026-05-17T01:28:13.485917+00:00",
    "item_id": "306913787569",
    "title": "10 Jim Kelly Cards Buffalo Bills Football Card Lot NFL",
    "added": [
      "Graded=No"
    ],
    "ok": true,
    "ack": "Success",
    "error": null,
    "error_code": null,
    "url": "https://www.ebay.com/itm/10-Jim-Kelly-Cards-Buffalo-Bills-Football-Card-Lot-NFL-/306913787569"
  },
  {
    "applied_at": "2026-05-17T01:28:15.393812+00:00",
    "item_id": "306913790653",
    "title": "11 Raghib And Quadry Ismail Cards Raiders Vikings",
    "added": [
      "Player=Raghib Quadry Ismail",
      "Athlete=Raghib Quadry Ismail",
      "Graded=No"
    ],
    "ok": true,
    "ack": "Success",
    "error": null,
    "error_code": null,
    "url": "https://www.ebay.com/itm/11-Raghib-And-Quadry-Ismail-Cards-Raiders-Vikings-/306913790653"
  },
  {
    "applied_at": "2026-05-17T01:28:17.857669+00:00",
    "item_id": "306913845449",
    "title": "3 Steve Largent Cards Seattle Seahawks Football Card Lot NFL",
    "added": [
      "Graded=No"
    ],
    "ok": true,
    "ack": "Success",
    "error": null,
    "error_code": null,
    "url": "https://www.ebay.com/itm/3-Steve-Largent-Cards-Seattle-Seahawks-Football-Card-Lot-NFL-/306913845449"
  },
  {
    "applied_at": "2026-05-17T01:28:20.847418+00:00",
    "item_id": "306913853080",
    "title": "9 Ronnie Lott Cards 49ers Raiders Jets Football Card Lot NFL",
    "added": [
      "Player=Ronnie Lott Raiders",
      "Athlete=Ronnie Lott Raiders",
      "Graded=No"
    ],
    "ok": true,
    "ack": "Success",
    "error": null,
    "error_code": null,
    "url": "https://www.ebay.com/itm/9-Ronnie-Lott-Cards-49ers-Raiders-Jets-Football-Card-Lot-NFL-/306913853080"
  },
  {
    "applied_at": "2026-05-17T01:28:23.836205+00:00",
    "item_id": "306913902750",
    "title": "7 Howie Long Cards Raiders",
    "added": [
      "Graded=No"
    ],
    "ok": true,
    "ack": "Success",
    "error": null,
    "error_code": null,
    "url": "https://www.ebay.com/itm/7-Howie-Long-Cards-Raiders-/306913902750"
  },
  {
    "applied_at": "2026-05-17T01:28:26.845024+00:00",
    "item_id": "306913908225",
    "title": "9 Joe Montana Cards 49ers Chiefs",
    "added": [
      "Graded=No"
    ],
    "ok": true,
    "ack": "Success",
    "error": null,
    "error_code": null,
    "url": "https://www.ebay.com/itm/9-Joe-Montana-Cards-49ers-Chiefs-/306913908225"
  },
  {
    "applied_at": "2026-05-17T01:28:30.381754+00:00",
    "item_id": "306933928667",
    "title": "2024 Panini Prizm Draft Picks - Gold Ice Prizm Lot (16 Cards)",
    "added": [
      "Year=2024",
      "Set=Prizm",
      "Player=Draft Picks Gold",
      "Athlete=Draft Picks Gold",
      "Parallel/Variety=Gold Ice",
      "Parallel=Gold Ice",
      "Graded=No"
    ],
    "ok": true,
    "ack": "Success",
    "error": null,
    "error_code": null,
    "url": "https://www.ebay.com/itm/2024-Panini-Prizm-Draft-Picks-Gold-Ice-Prizm-Lot-16-Cards--/306933928667"
  },
  {
    "applied_at": "2026-05-17T01:28:32.205846+00:00",
    "item_id": "306934532731",
    "title": "3 Neon Green Pulsar and 5 Purple Wave Prizm 2025 Cards",
    "added": [
      "Year=2025",
      "Manufacturer=Panini",
      "Set=Prizm",
      "Player=Neon Green Pulsar",
      "Athlete=Neon Green Pulsar",
      "Graded=No"
    ],
    "ok": true,
    "ack": "Success",
    "error": null,
    "error_code": null,
    "url": "https://www.ebay.com/itm/3-Neon-Green-Pulsar-and-5-Purple-Wave-Prizm-2025-Cards-/306934532731"
  },
  {
    "applied_at": "2026-05-17T01:28:34.622275+00:00",
    "item_id": "306937452121",
    "title": "2026 Wild Card- Joe Burrow & Justin Jefferson Card 1/1 King",
    "added": [
      "Year=2026",
      "Graded=No"
    ],
    "ok": true,
    "ack": "Success",
    "error": null,
    "error_code": null,
    "url": "https://www.ebay.com/itm/2026-Wild-Card-Joe-Burrow-Justin-Jefferson-Card-1-1-King-/306937452121"
  },
  {
    "applied_at": "2026-05-17T01:28:36.525487+00:00",
    "item_id": "306937463442",
    "title": "2026 Wild Card 5 Card Draw Garrett Nussmeier RC 1/2 Silver Holo Queen",
    "added": [
      "Year=2026",
      "Graded=No"
    ],
    "ok": true,
    "ack": "Success",
    "error": null,
    "error_code": null,
    "url": "https://www.ebay.com/itm/2026-Wild-Card-5-Card-Draw-Garrett-Nussmeier-RC-1-2-Silver-Holo-Queen-/306937463442"
  },
  {
    "applied_at": "2026-05-17T01:28:38.978310+00:00",
    "item_id": "306937466251",
    "title": "2026 Wild Card 5 Card Draw Stacked Deck Jeremiyah Love RC 3/5 Silver Holo Rookie",
    "added": [
      "Year=2026",
      "Graded=No"
    ],
    "ok": true,
    "ack": "Success",
    "error": null,
    "error_code": null,
    "url": "https://www.ebay.com/itm/2026-Wild-Card-5-Card-Draw-Stacked-Deck-Jeremiyah-Love-RC-3-5-Silver-Holo-Rookie-/306937466251"
  },
  {
    "applied_at": "2026-05-17T01:28:40.416162+00:00",
    "item_id": "306937601406",
    "title": "2025 Panini Select - Concourse Chuba Hubbard #43 Zebra Prizm",
    "added": [
      "Year=2025",
      "Graded=No"
    ],
    "ok": false,
    "ack": "Failure",
    "error": "Listing cannot be revised.",
    "error_code": "21916743",
    "url": "https://www.ebay.com/itm/2025-Panini-Select-Concourse-Chuba-Hubbard-43-Zebra-Prizm-/306937601406"
  },
  {
    "applied_at": "2026-05-17T01:28:43.337653+00:00",
    "item_id": "306937606464",
    "title": "2025 Topps Update Series - 1990 Topps Baseball Marcelo Mayer #U90-9 Green...",
    "added": [
      "Year=2025",
      "Graded=No"
    ],
    "ok": true,
    "ack": "Warning",
    "error": "Some custom Item Specific(s) were overwritten by Product Item Specific(s)",
    "error_code": "21920270",
    "url": "https://www.ebay.com/itm/2025-Topps-Update-Series-1990-Topps-Baseball-Marcelo-Mayer-U90-9-Green--/306937606464"
  },
  {
    "applied_at": "2026-05-17T01:28:45.842735+00:00",
    "item_id": "306903937710",
    "title": "Jerome Bettis Notre Dame Los Angeles Rams 10 Cards",
    "added": [
      "Player=Jerome Bettis Notre",
      "Athlete=Jerome Bettis Notre",
      "Graded=No"
    ],
    "ok": true,
    "ack": "Success",
    "error": null,
    "error_code": null,
    "url": "https://www.ebay.com/itm/Jerome-Bettis-Notre-Dame-Los-Angeles-Rams-10-Cards-/306903937710"
  },
  {
    "applied_at": "2026-05-17T01:28:48.908869+00:00",
    "item_id": "306903941543",
    "title": "Tim Brown Los Angeles Raiders Football Card Lot (14) HOF Wide Receiver",
    "added": [
      "Graded=No"
    ],
    "ok": true,
    "ack": "Success",
    "error": null,
    "error_code": null,
    "url": "https://www.ebay.com/itm/Tim-Brown-Los-Angeles-Raiders-Football-Card-Lot-14-HOF-Wide-Receiver-/306903941543"
  },
  {
    "applied_at": "2026-05-17T01:28:50.700087+00:00",
    "item_id": "306903947932",
    "title": "Carl Banks New York Giants Football Card Lot (8) Super Bowl LB",
    "added": [
      "Graded=No"
    ],
    "ok": true,
    "ack": "Success",
    "error": null,
    "error_code": null,
    "url": "https://www.ebay.com/itm/Carl-Banks-New-York-Giants-Football-Card-Lot-8-Super-Bowl-LB-/306903947932"
  },
  {
    "applied_at": "2026-05-17T01:28:53.321263+00:00",
    "item_id": "306904068997",
    "title": "11 Cards Marcus Allen Los Angeles Raiders Kansas City Chiefs",
    "added": [
      "Graded=No"
    ],
    "ok": true,
    "ack": "Success",
    "error": null,
    "error_code": null,
    "url": "https://www.ebay.com/itm/11-Cards-Marcus-Allen-Los-Angeles-Raiders-Kansas-City-Chiefs-/306904068997"
  },
  {
    "applied_at": "2026-05-17T01:28:55.875858+00:00",
    "item_id": "306904078786",
    "title": "7 Cards Steve Atwater Rookie Cards Denver Broncos",
    "added": [
      "Player=Steve Atwater Denver",
      "Athlete=Steve Atwater Denver",
      "Graded=No"
    ],
    "ok": true,
    "ack": "Success",
    "error": null,
    "error_code": null,
    "url": "https://www.ebay.com/itm/7-Cards-Steve-Atwater-Rookie-Cards-Denver-Broncos-/306904078786"
  },
  {
    "applied_at": "2026-05-17T01:28:58.888435+00:00",
    "item_id": "306904174454",
    "title": "7 Cards Boomer Esiason Cincinnati Bengals New York Jets",
    "added": [
      "Graded=No"
    ],
    "ok": true,
    "ack": "Success",
    "error": null,
    "error_code": null,
    "url": "https://www.ebay.com/itm/7-Cards-Boomer-Esiason-Cincinnati-Bengals-New-York-Jets-/306904174454"
  },
  {
    "applied_at": "2026-05-17T01:29:00.690427+00:00",
    "item_id": "306904189481",
    "title": "4 Aaron Glenn Rookie Cards New York Jets",
    "added": [
      "Player=Aaron Glenn New",
      "Athlete=Aaron Glenn New",
      "Graded=No"
    ],
    "ok": true,
    "ack": "Success",
    "error": null,
    "error_code": null,
    "url": "https://www.ebay.com/itm/4-Aaron-Glenn-Rookie-Cards-New-York-Jets-/306904189481"
  },
  {
    "applied_at": "2026-05-17T01:29:03.966227+00:00",
    "item_id": "306904203738",
    "title": "1994 Classic Pro Line Live - Autograph - Steve Emtman",
    "added": [
      "Year=1994"
    ],
    "ok": true,
    "ack": "Warning",
    "error": "Some custom Item Specific(s) were overwritten by Product Item Specific(s)",
    "error_code": "21920270",
    "url": "https://www.ebay.com/itm/1994-Classic-Pro-Line-Live-Autograph-Steve-Emtman--/306904203738"
  },
  {
    "applied_at": "2026-05-17T01:29:06.387692+00:00",
    "item_id": "306904215389",
    "title": "12 Jim Everett Cards Los Angeles Rams New Orleans Saints",
    "added": [
      "Graded=No"
    ],
    "ok": true,
    "ack": "Success",
    "error": null,
    "error_code": null,
    "url": "https://www.ebay.com/itm/12-Jim-Everett-Cards-Los-Angeles-Rams-New-Orleans-Saints-/306904215389"
  },
  {
    "applied_at": "2026-05-17T01:29:09.552024+00:00",
    "item_id": "306913168494",
    "title": "15 Charles Haley Cards San Francisco 49ers Dallas Cowboys",
    "added": [
      "Player=Charles Haley San",
      "Athlete=Charles Haley San",
      "Graded=No"
    ],
    "ok": true,
    "ack": "Success",
    "error": null,
    "error_code": null,
    "url": "https://www.ebay.com/itm/15-Charles-Haley-Cards-San-Francisco-49ers-Dallas-Cowboys-/306913168494"
  },
  {
    "applied_at": "2026-05-17T01:29:11.444122+00:00",
    "item_id": "306913186982",
    "title": "11 Mel Gray Cards Detroit Lions Football Card Lot NFL",
    "added": [
      "Graded=No"
    ],
    "ok": true,
    "ack": "Success",
    "error": null,
    "error_code": null,
    "url": "https://www.ebay.com/itm/11-Mel-Gray-Cards-Detroit-Lions-Football-Card-Lot-NFL-/306913186982"
  },
  {
    "applied_at": "2026-05-17T01:29:13.389388+00:00",
    "item_id": "306913307606",
    "title": "5 Bobby Humphrey Cards Denver Broncos Football Card Lot NFL",
    "added": [
      "Graded=No"
    ],
    "ok": true,
    "ack": "Success",
    "error": null,
    "error_code": null,
    "url": "https://www.ebay.com/itm/5-Bobby-Humphrey-Cards-Denver-Broncos-Football-Card-Lot-NFL-/306913307606"
  },
  {
    "applied_at": "2026-05-17T01:29:15.231348+00:00",
    "item_id": "306913787569",
    "title": "10 Jim Kelly Cards Buffalo Bills Football Card Lot NFL",
    "added": [
      "Graded=No"
    ],
    "ok": true,
    "ack": "Success",
    "error": null,
    "error_code": null,
    "url": "https://www.ebay.com/itm/10-Jim-Kelly-Cards-Buffalo-Bills-Football-Card-Lot-NFL-/306913787569"
  },
  {
    "applied_at": "2026-05-17T01:29:17.074969+00:00",
    "item_id": "306913790653",
    "title": "11 Raghib And Quadry Ismail Cards Raiders Vikings",
    "added": [
      "Player=Raghib Quadry Ismail",
      "Athlete=Raghib Quadry Ismail",
      "Graded=No"
    ],
    "ok": true,
    "ack": "Success",
    "error": null,
    "error_code": null,
    "url": "https://www.ebay.com/itm/11-Raghib-And-Quadry-Ismail-Cards-Raiders-Vikings-/306913790653"
  },
  {
    "applied_at": "2026-05-17T01:29:19.954038+00:00",
    "item_id": "306913845449",
    "title": "3 Steve Largent Cards Seattle Seahawks Football Card Lot NFL",
    "added": [
      "Graded=No"
    ],
    "ok": true,
    "ack": "Success",
    "error": null,
    "error_code": null,
    "url": "https://www.ebay.com/itm/3-Steve-Largent-Cards-Seattle-Seahawks-Football-Card-Lot-NFL-/306913845449"
  },
  {
    "applied_at": "2026-05-17T01:29:21.785011+00:00",
    "item_id": "306913853080",
    "title": "9 Ronnie Lott Cards 49ers Raiders Jets Football Card Lot NFL",
    "added": [
      "Player=Ronnie Lott Raiders",
      "Athlete=Ronnie Lott Raiders",
      "Graded=No"
    ],
    "ok": true,
    "ack": "Success",
    "error": null,
    "error_code": null,
    "url": "https://www.ebay.com/itm/9-Ronnie-Lott-Cards-49ers-Raiders-Jets-Football-Card-Lot-NFL-/306913853080"
  },
  {
    "applied_at": "2026-05-17T01:29:23.627376+00:00",
    "item_id": "306913902750",
    "title": "7 Howie Long Cards Raiders",
    "added": [
      "Graded=No"
    ],
    "ok": true,
    "ack": "Success",
    "error": null,
    "error_code": null,
    "url": "https://www.ebay.com/itm/7-Howie-Long-Cards-Raiders-/306913902750"
  },
  {
    "applied_at": "2026-05-17T01:29:26.700754+00:00",
    "item_id": "306913908225",
    "title": "9 Joe Montana Cards 49ers Chiefs",
    "added": [
      "Graded=No"
    ],
    "ok": true,
    "ack": "Success",
    "error": null,
    "error_code": null,
    "url": "https://www.ebay.com/itm/9-Joe-Montana-Cards-49ers-Chiefs-/306913908225"
  },
  {
    "applied_at": "2026-05-17T01:29:30.751879+00:00",
    "item_id": "306933928667",
    "title": "2024 Panini Prizm Draft Picks - Gold Ice Prizm Lot (16 Cards)",
    "added": [
      "Year=2024",
      "Set=Prizm",
      "Player=Draft Picks Gold",
      "Athlete=Draft Picks Gold",
      "Parallel/Variety=Gold Ice",
      "Parallel=Gold Ice",
      "Graded=No"
    ],
    "ok": true,
    "ack": "Success",
    "error": null,
    "error_code": null,
    "url": "https://www.ebay.com/itm/2024-Panini-Prizm-Draft-Picks-Gold-Ice-Prizm-Lot-16-Cards--/306933928667"
  },
  {
    "applied_at": "2026-05-17T01:29:32.551807+00:00",
    "item_id": "306934532731",
    "title": "3 Neon Green Pulsar and 5 Purple Wave Prizm 2025 Cards",
    "added": [
      "Year=2025",
      "Manufacturer=Panini",
      "Set=Prizm",
      "Player=Neon Green Pulsar",
      "Athlete=Neon Green Pulsar",
      "Graded=No"
    ],
    "ok": true,
    "ack": "Success",
    "error": null,
    "error_code": null,
    "url": "https://www.ebay.com/itm/3-Neon-Green-Pulsar-and-5-Purple-Wave-Prizm-2025-Cards-/306934532731"
  },
  {
    "applied_at": "2026-05-17T01:29:34.993483+00:00",
    "item_id": "306937452121",
    "title": "2026 Wild Card- Joe Burrow & Justin Jefferson Card 1/1 King",
    "added": [
      "Year=2026",
      "Graded=No"
    ],
    "ok": true,
    "ack": "Success",
    "error": null,
    "error_code": null,
    "url": "https://www.ebay.com/itm/2026-Wild-Card-Joe-Burrow-Justin-Jefferson-Card-1-1-King-/306937452121"
  },
  {
    "applied_at": "2026-05-17T01:29:37.573453+00:00",
    "item_id": "306937463442",
    "title": "2026 Wild Card 5 Card Draw Garrett Nussmeier RC 1/2 Silver Holo Queen",
    "added": [
      "Year=2026",
      "Graded=No"
    ],
    "ok": true,
    "ack": "Success",
    "error": null,
    "error_code": null,
    "url": "https://www.ebay.com/itm/2026-Wild-Card-5-Card-Draw-Garrett-Nussmeier-RC-1-2-Silver-Holo-Queen-/306937463442"
  },
  {
    "applied_at": "2026-05-17T01:29:40.115072+00:00",
    "item_id": "306937466251",
    "title": "2026 Wild Card 5 Card Draw Stacked Deck Jeremiyah Love RC 3/5 Silver Holo Rookie",
    "added": [
      "Year=2026",
      "Graded=No"
    ],
    "ok": true,
    "ack": "Success",
    "error": null,
    "error_code": null,
    "url": "https://www.ebay.com/itm/2026-Wild-Card-5-Card-Draw-Stacked-Deck-Jeremiyah-Love-RC-3-5-Silver-Holo-Rookie-/306937466251"
  },
  {
    "applied_at": "2026-05-17T01:29:41.678012+00:00",
    "item_id": "306937601406",
    "title": "2025 Panini Select - Concourse Chuba Hubbard #43 Zebra Prizm",
    "added": [
      "Year=2025",
      "Graded=No"
    ],
    "ok": false,
    "ack": "Failure",
    "error": "Listing cannot be revised.",
    "error_code": "21916743",
    "url": "https://www.ebay.com/itm/2025-Panini-Select-Concourse-Chuba-Hubbard-43-Zebra-Prizm-/306937601406"
  },
  {
    "applied_at": "2026-05-17T01:29:44.791586+00:00",
    "item_id": "306937606464",
    "title": "2025 Topps Update Series - 1990 Topps Baseball Marcelo Mayer #U90-9 Green...",
    "added": [
      "Year=2025",
      "Graded=No"
    ],
    "ok": true,
    "ack": "Warning",
    "error": "Some custom Item Specific(s) were overwritten by Product Item Specific(s)",
    "error_code": "21920270",
    "url": "https://www.ebay.com/itm/2025-Topps-Update-Series-1990-Topps-Baseball-Marcelo-Mayer-U90-9-Green--/306937606464"
  },
  {
    "applied_at": "2026-05-17T01:29:47.867748+00:00",
    "item_id": "306903937710",
    "title": "Jerome Bettis Notre Dame Los Angeles Rams 10 Cards",
    "added": [
      "Player=Jerome Bettis Notre",
      "Athlete=Jerome Bettis Notre",
      "Graded=No"
    ],
    "ok": true,
    "ack": "Success",
    "error": null,
    "error_code": null,
    "url": "https://www.ebay.com/itm/Jerome-Bettis-Notre-Dame-Los-Angeles-Rams-10-Cards-/306903937710"
  },
  {
    "applied_at": "2026-05-17T01:29:50.867186+00:00",
    "item_id": "306903941543",
    "title": "Tim Brown Los Angeles Raiders Football Card Lot (14) HOF Wide Receiver",
    "added": [
      "Graded=No"
    ],
    "ok": true,
    "ack": "Success",
    "error": null,
    "error_code": null,
    "url": "https://www.ebay.com/itm/Tim-Brown-Los-Angeles-Raiders-Football-Card-Lot-14-HOF-Wide-Receiver-/306903941543"
  },
  {
    "applied_at": "2026-05-17T01:29:52.628817+00:00",
    "item_id": "306903947932",
    "title": "Carl Banks New York Giants Football Card Lot (8) Super Bowl LB",
    "added": [
      "Graded=No"
    ],
    "ok": true,
    "ack": "Success",
    "error": null,
    "error_code": null,
    "url": "https://www.ebay.com/itm/Carl-Banks-New-York-Giants-Football-Card-Lot-8-Super-Bowl-LB-/306903947932"
  },
  {
    "applied_at": "2026-05-17T01:29:55.166772+00:00",
    "item_id": "306904068997",
    "title": "11 Cards Marcus Allen Los Angeles Raiders Kansas City Chiefs",
    "added": [
      "Graded=No"
    ],
    "ok": true,
    "ack": "Success",
    "error": null,
    "error_code": null,
    "url": "https://www.ebay.com/itm/11-Cards-Marcus-Allen-Los-Angeles-Raiders-Kansas-City-Chiefs-/306904068997"
  },
  {
    "applied_at": "2026-05-17T01:29:58.238816+00:00",
    "item_id": "306904078786",
    "title": "7 Cards Steve Atwater Rookie Cards Denver Broncos",
    "added": [
      "Player=Steve Atwater Denver",
      "Athlete=Steve Atwater Denver",
      "Graded=No"
    ],
    "ok": true,
    "ack": "Success",
    "error": null,
    "error_code": null,
    "url": "https://www.ebay.com/itm/7-Cards-Steve-Atwater-Rookie-Cards-Denver-Broncos-/306904078786"
  },
  {
    "applied_at": "2026-05-17T01:30:00.122804+00:00",
    "item_id": "306904174454",
    "title": "7 Cards Boomer Esiason Cincinnati Bengals New York Jets",
    "added": [
      "Graded=No"
    ],
    "ok": true,
    "ack": "Success",
    "error": null,
    "error_code": null,
    "url": "https://www.ebay.com/itm/7-Cards-Boomer-Esiason-Cincinnati-Bengals-New-York-Jets-/306904174454"
  },
  {
    "applied_at": "2026-05-17T01:30:03.154580+00:00",
    "item_id": "306904189481",
    "title": "4 Aaron Glenn Rookie Cards New York Jets",
    "added": [
      "Player=Aaron Glenn New",
      "Athlete=Aaron Glenn New",
      "Graded=No"
    ],
    "ok": true,
    "ack": "Success",
    "error": null,
    "error_code": null,
    "url": "https://www.ebay.com/itm/4-Aaron-Glenn-Rookie-Cards-New-York-Jets-/306904189481"
  },
  {
    "applied_at": "2026-05-17T01:30:05.702560+00:00",
    "item_id": "306904203738",
    "title": "1994 Classic Pro Line Live - Autograph - Steve Emtman",
    "added": [
      "Year=1994"
    ],
    "ok": true,
    "ack": "Warning",
    "error": "Some custom Item Specific(s) were overwritten by Product Item Specific(s)",
    "error_code": "21920270",
    "url": "https://www.ebay.com/itm/1994-Classic-Pro-Line-Live-Autograph-Steve-Emtman--/306904203738"
  },
  {
    "applied_at": "2026-05-17T01:30:08.247458+00:00",
    "item_id": "306904215389",
    "title": "12 Jim Everett Cards Los Angeles Rams New Orleans Saints",
    "added": [
      "Graded=No"
    ],
    "ok": true,
    "ack": "Success",
    "error": null,
    "error_code": null,
    "url": "https://www.ebay.com/itm/12-Jim-Everett-Cards-Los-Angeles-Rams-New-Orleans-Saints-/306904215389"
  },
  {
    "applied_at": "2026-05-17T01:30:10.260615+00:00",
    "item_id": "306913168494",
    "title": "15 Charles Haley Cards San Francisco 49ers Dallas Cowboys",
    "added": [
      "Player=Charles Haley San",
      "Athlete=Charles Haley San",
      "Graded=No"
    ],
    "ok": true,
    "ack": "Success",
    "error": null,
    "error_code": null,
    "url": "https://www.ebay.com/itm/15-Charles-Haley-Cards-San-Francisco-49ers-Dallas-Cowboys-/306913168494"
  },
  {
    "applied_at": "2026-05-17T01:30:12.780028+00:00",
    "item_id": "306913186982",
    "title": "11 Mel Gray Cards Detroit Lions Football Card Lot NFL",
    "added": [
      "Graded=No"
    ],
    "ok": true,
    "ack": "Success",
    "error": null,
    "error_code": null,
    "url": "https://www.ebay.com/itm/11-Mel-Gray-Cards-Detroit-Lions-Football-Card-Lot-NFL-/306913186982"
  },
  {
    "applied_at": "2026-05-17T01:30:15.831357+00:00",
    "item_id": "306913307606",
    "title": "5 Bobby Humphrey Cards Denver Broncos Football Card Lot NFL",
    "added": [
      "Graded=No"
    ],
    "ok": true,
    "ack": "Success",
    "error": null,
    "error_code": null,
    "url": "https://www.ebay.com/itm/5-Bobby-Humphrey-Cards-Denver-Broncos-Football-Card-Lot-NFL-/306913307606"
  },
  {
    "applied_at": "2026-05-17T01:30:18.823813+00:00",
    "item_id": "306913787569",
    "title": "10 Jim Kelly Cards Buffalo Bills Football Card Lot NFL",
    "added": [
      "Graded=No"
    ],
    "ok": true,
    "ack": "Success",
    "error": null,
    "error_code": null,
    "url": "https://www.ebay.com/itm/10-Jim-Kelly-Cards-Buffalo-Bills-Football-Card-Lot-NFL-/306913787569"
  },
  {
    "applied_at": "2026-05-17T01:30:21.384832+00:00",
    "item_id": "306913790653",
    "title": "11 Raghib And Quadry Ismail Cards Raiders Vikings",
    "added": [
      "Player=Raghib Quadry Ismail",
      "Athlete=Raghib Quadry Ismail",
      "Graded=No"
    ],
    "ok": true,
    "ack": "Success",
    "error": null,
    "error_code": null,
    "url": "https://www.ebay.com/itm/11-Raghib-And-Quadry-Ismail-Cards-Raiders-Vikings-/306913790653"
  },
  {
    "applied_at": "2026-05-17T01:30:24.045014+00:00",
    "item_id": "306913845449",
    "title": "3 Steve Largent Cards Seattle Seahawks Football Card Lot NFL",
    "added": [
      "Graded=No"
    ],
    "ok": true,
    "ack": "Success",
    "error": null,
    "error_code": null,
    "url": "https://www.ebay.com/itm/3-Steve-Largent-Cards-Seattle-Seahawks-Football-Card-Lot-NFL-/306913845449"
  },
  {
    "applied_at": "2026-05-17T01:30:27.012521+00:00",
    "item_id": "306913853080",
    "title": "9 Ronnie Lott Cards 49ers Raiders Jets Football Card Lot NFL",
    "added": [
      "Player=Ronnie Lott Raiders",
      "Athlete=Ronnie Lott Raiders",
      "Graded=No"
    ],
    "ok": true,
    "ack": "Success",
    "error": null,
    "error_code": null,
    "url": "https://www.ebay.com/itm/9-Ronnie-Lott-Cards-49ers-Raiders-Jets-Football-Card-Lot-NFL-/306913853080"
  },
  {
    "applied_at": "2026-05-17T01:30:29.987337+00:00",
    "item_id": "306913902750",
    "title": "7 Howie Long Cards Raiders",
    "added": [
      "Graded=No"
    ],
    "ok": true,
    "ack": "Success",
    "error": null,
    "error_code": null,
    "url": "https://www.ebay.com/itm/7-Howie-Long-Cards-Raiders-/306913902750"
  },
  {
    "applied_at": "2026-05-17T01:30:31.826476+00:00",
    "item_id": "306913908225",
    "title": "9 Joe Montana Cards 49ers Chiefs",
    "added": [
      "Graded=No"
    ],
    "ok": true,
    "ack": "Success",
    "error": null,
    "error_code": null,
    "url": "https://www.ebay.com/itm/9-Joe-Montana-Cards-49ers-Chiefs-/306913908225"
  }
]